{
  "page-programs-showing-all": "Showing All Programs",
  "page-programs-showing": "Showing",
  "page-programs-programs": "Programs",
  "page-programs-sort-by": "Sort By...",
  "page-programs-sort-default": "Default Sort",
  "page-programs-sort-alphabetical": "Alphabetical Sort",

  "comp-programs-metadata-minute-read": "minute read",
  "comp-programs-metadata-tip-author": "Tip author",
  "page-programs-read-time": "min",
  "page-programs-submit-btn": "Submit a tutorial",

  "page-programs-external-link": "External",

  "page-programs-beginner": "Beginner",
  "page-programs-survive": "Survive",
  "page-programs-intermediate": "Intermediate",
  "page-programs-advanced": "Advanced",

  "page-programs-profile-filters": "Profiles",
  "page-programs-advanced-filters": "Filters",

  "page-programs-reset-filters": "Reset All Filters",
  "page-programs-filter-error": "No programs with all your chosen filters (yet).",
  "page-programs-try-removing-filters": "Try removing a filter or two, or add to our repository!",
  "page-programs-tags-reset": "Reset Tags",

  "page-programs-submit-button": "Submit Program",
  "page-programs-submit-description": "To submit a program, you'll need to use GitHub. We welcome you to create an issue or a pull request to submit articles or links to external programs.",
  "page-programs-new-github": "New to GitHub?",
  "page-programs-new-github-description": "Raise an issue – simply fill in the requested information in the form and paste your program details.",
  "page-programs-raise-issue-button": "Raise Issue",
  "page-programs-pull-request": "Create A Pull Request",
  "page-programs-pull-request-button": "Pull Request",
  "page-programs-pull-request-description": "Please make changes on your local version and follow the naming structure for submission.",

  "page-programs-filters-description": "What Are You Experiencing?",
  
  "page-programs-profile-1-title": "Lack Of Motivation",
  "page-programs-profile-1-description": "I can't seem to concentrate on the things I need to do.",
  "page-programs-profile-2-title": "Frustrated At Others",
  "page-programs-profile-2-description": "I don't understand why others can't just see it my way.",
  "page-programs-profile-3-title": "Feeling Helpless",
  "page-programs-profile-3-description": "I lack confidence in myself and my capability.",
  "page-programs-profile-4-title": "Not Achieving My Goals",
  "page-programs-profile-4-description": "I fall short of being able to achieve what I want to do.",

  "page-tutorials-env-banner": "Don't commit <code>.env</code>! Please make sure never to share or expose your <code>.env</code> file with anyone, as you are compromising your secrets in doing so. If you are using version control, add your <code>.env</code> to a <a href=\"https://git-scm.com/docs/gitignore\">gitignore</a> file."
}